monkeyhex.py
monkeyhex-1.2.dist-info/DESCRIPTION.rst
monkeyhex-1.2.dist-info/METADATA
monkeyhex-1.2.dist-info/RECORD
monkeyhex-1.2.dist-info/WHEEL
monkeyhex-1.2.dist-info/metadata.json
monkeyhex-1.2.dist-info/top_level.txt
