Metadata-Version: 2.0
Name: monkeyhex
Version: 1.2
Summary: Monkeypatch the python interpreter to print integer results in hex
Home-page: https://github.com/rhelmot/monkeyhex
Author: Andrew Dutcher
Author-email: andrew@andrewdutcher.com
License: MIT
Keywords: hex hexadecimal monkeypatch integer number interpreter result
Platform: UNKNOWN
